fastapi_vite/__init__.py
fastapi_vite/cli.py
fastapi_vite/config.py
fastapi_vite/loader.py
fastapi_vite-0.3.2.dist-info/entry_points.txt
fastapi_vite-0.3.2.dist-info/WHEEL
fastapi_vite-0.3.2.dist-info/METADATA
fastapi_vite-0.3.2.dist-info/RECORD
