Metadata-Version: 2.1
Name: fastapi-vite
Version: 0.3.2
Summary: Integration utilities for FastAPI and ViteJS.
Home-page: https://github.com/cofin/fastapi-vite
License: MIT
Keywords: fastapi,starlette,vite
Author: Cody Fincher
Author-email: cody.fincher@gmail.com
Requires-Python: >=3.8,<4
Classifier: Framework :: AsyncIO
Classifier: Intended Audience :: Developers
Classifier: License :: OSI Approved :: MIT License
Classifier: Programming Language :: Python :: 3
Classifier: Programming Language :: Python :: 3 :: Only
Classifier: Programming Language :: Python :: 3.10
Classifier: Programming Language :: Python :: 3.8
Classifier: Programming Language :: Python :: 3.9
Requires-Dist: Jinja2
Requires-Dist: fastapi
Requires-Dist: pydantic[dotenv] (>=1.9.0,<2.0.0)
Requires-Dist: typer
Project-URL: Repository, https://github.com/cofin/fastapi-vite
